simpleautogui/__init__.py
simpleautogui/notify.py
simpleautogui/screen/__init__.py
simpleautogui/screen/utils.py
simpleautogui/screen/classes/__init__.py
simpleautogui/screen/classes/base.py
simpleautogui/win/__init__.py
simpleautogui/win/console/base.py
simpleautogui/win/console/exceptions/base.py
simpleautogui/win/windows/__init__.py
simpleautogui/win/windows/classes.py
simpleautogui/win/windows/exceptions/base.py
simpleautogui-0.0.6.dist-info/LICENSE
simpleautogui-0.0.6.dist-info/METADATA
simpleautogui-0.0.6.dist-info/WHEEL
simpleautogui-0.0.6.dist-info/top_level.txt
simpleautogui-0.0.6.dist-info/RECORD
