Metadata-Version: 2.1
Name: simpleautogui
Version: 0.0.6
Summary: A library that greatly simplifies the automation of the Windows graphical interface.
Author-email: artasov <ivanhvalevskey@gmail.com>
Project-URL: Homepage, https://github.com/Artasov/simpleautogui
Project-URL: Issues, https://github.com/Artasov/simpleautogui/issues
Classifier: Development Status :: 3 - Alpha
Classifier: Programming Language :: Python :: 3
Classifier: License :: OSI Approved :: MIT License
Classifier: Operating System :: Microsoft :: Windows
Requires-Python: >=3.11
License-File: LICENSE
Requires-Dist: PyAutoGUI >=0.9.54
Requires-Dist: opencv-python >=4.9.0.80
Requires-Dist: pywin32 >=306
Requires-Dist: pytesseract >=0.3.1
Requires-Dist: mouse >=0.7.1
Requires-Dist: webcolors >=1.13
Requires-Dist: keyboard >=0.13.5
Requires-Dist: pydub >=0.25.1
Requires-Dist: pillow >=10.3.0
